paginated
