Metadata-Version: 1.0
Name: django-paginated
Version: 0.1.4
Summary: Simple django digg-style pagination.
Home-page: http://github.com/simas/django-paginated
Author: Simas Skrebiškis
Author-email: simas.skrebiskis@gmail.com
License: MIT
Platform: UNKNOWN
